pedestrian_movement/__init__.py
pedestrian_movement/model_pedestrian.py
pedestrian_movement-0.0.1.dist-info/LICENSE
pedestrian_movement-0.0.1.dist-info/METADATA
pedestrian_movement-0.0.1.dist-info/WHEEL
pedestrian_movement-0.0.1.dist-info/top_level.txt
pedestrian_movement-0.0.1.dist-info/RECORD
